pyswan/__init__.py
pyswan/_version.py
pyswan/api.py
pyswan/classifier.py
pyswan/constants.py
pyswan/extract_cpca.py
pyswan/extract_math_equation.py
pyswan/extract_number.py
pyswan/extract_time.py
pyswan/gen_number.py
pyswan/gen_time.py
pyswan/keywords.py
pyswan/message.py
pyswan/normative.py
pyswan/numeral.py
pyswan/parser.py
pyswan-0.4.0.dist-info/LICENSE
pyswan-0.4.0.dist-info/METADATA
pyswan-0.4.0.dist-info/WHEEL
pyswan-0.4.0.dist-info/top_level.txt
pyswan-0.4.0.dist-info/RECORD
