Metadata-Version: 2.1
Name: pyswan
Version: 0.4.0
Summary: Better dates, times, math expression and place extractor for Python of Chinese
Home-page: https://github.com/JosiahMg/pyswan
Author: Josiah Meng
Author-email: josiahmg@163.com
License: Apache 2.0
Project-URL: Repository, https://github.com/JosiahMg/pyswan
Project-URL: Bug Reports, https://github.com/JosiahMg/pyswan/issues
Project-URL: Documentation, https://github.com/JosiahMg/pyswan
Keywords: pyswan Chinese date time
Platform: UNKNOWN
Classifier: Development Status :: 5 - Production/Stable
Classifier: Intended Audience :: Developers
Classifier: License :: OSI Approved :: Apache Software License
Classifier: Topic :: Software Development :: Libraries :: Python Modules
Classifier: Programming Language :: Python :: 3
Classifier: Programming Language :: Python :: 3 :: Only
Classifier: Programming Language :: Python :: 3.6
Classifier: Programming Language :: Python :: 3.7
Classifier: Programming Language :: Python :: 3.8
Classifier: Programming Language :: Python :: 3.9
Classifier: Programming Language :: Python :: 3.10
Requires-Python: >=3.6
Requires-Dist: arrow (>=1.1.0)
Requires-Dist: typing-extensions ; python_version < "3.9"
